wordlebee/__about__.py
wordlebee/__init__.py
wordlebee/__main__.py
wordlebee/data/extended.txt
wordlebee/data/extended_filtered.txt
wordlebee/data/popular.txt
wordlebee/data/popular_filtered.txt
wordlebee/data/words.txt
wordlebee/data/words_filtered.txt
wordlebee/filter_words.py
wordlebee-0.7.4.dist-info/entry_points.txt
wordlebee-0.7.4.dist-info/LICENSE
wordlebee-0.7.4.dist-info/WHEEL
wordlebee-0.7.4.dist-info/METADATA
wordlebee-0.7.4.dist-info/RECORD
