Metadata-Version: 2.1
Name: wordlebee
Version: 0.7.4
Summary: wordle word guessing helper bee
License: MIT
Keywords: wordle,cli
Author: Mrlento234
Author-email: lento.manickathan@gmail.com
Requires-Python: >=3.9,<4.0
Classifier: Environment :: Console
Classifier: License :: OSI Approved :: MIT License
Classifier: Operating System :: POSIX :: Linux
Classifier: Programming Language :: Python :: 3
Classifier: Programming Language :: Python :: 3.10
Classifier: Programming Language :: Python :: 3.8
Classifier: Programming Language :: Python :: 3.9
Requires-Dist: numpy (>=1.22.3,<2.0.0)
Requires-Dist: rich (>=12.0.1,<13.0.0)
